{
  "openapi": "3.0.3",
  "info": {
    "title": "ModSemi Sample API",
    "description": "示範用 Swagger / OpenAPI 規格，用於測試 orval 程式碼生成。",
    "version": "1.0.0"
  },
  "servers": [
    {
      "url": "/api",
      "description": "本地開發伺服器"
    }
  ],
  "tags": [
    { "name": "User", "description": "使用者管理" },
    { "name": "Article", "description": "文章管理" }
  ],
  "paths": {
    "/users": {
      "get": {
        "tags": ["User"],
        "summary": "取得使用者列表",
        "operationId": "getUsers",
        "parameters": [
          {
            "name": "page",
            "in": "query",
            "schema": { "type": "integer", "default": 1 }
          },
          {
            "name": "pageSize",
            "in": "query",
            "schema": { "type": "integer", "default": 20 }
          },
          {
            "name": "keyword",
            "in": "query",
            "schema": { "type": "string" }
          }
        ],
        "responses": {
          "200": {
            "description": "成功",
            "content": {
              "application/json": {
                "schema": { "$ref": "#/components/schemas/UserListResponse" }
              }
            }
          }
        }
      },
      "post": {
        "tags": ["User"],
        "summary": "建立使用者",
        "operationId": "createUser",
        "requestBody": {
          "required": true,
          "content": {
            "application/json": {
              "schema": { "$ref": "#/components/schemas/CreateUserRequest" }
            }
          }
        },
        "responses": {
          "201": {
            "description": "建立成功",
            "content": {
              "application/json": {
                "schema": { "$ref": "#/components/schemas/User" }
              }
            }
          }
        }
      }
    },
    "/users/{id}": {
      "get": {
        "tags": ["User"],
        "summary": "取得單一使用者",
        "operationId": "getUserById",
        "parameters": [
          {
            "name": "id",
            "in": "path",
            "required": true,
            "schema": { "type": "integer" }
          }
        ],
        "responses": {
          "200": {
            "description": "成功",
            "content": {
              "application/json": {
                "schema": { "$ref": "#/components/schemas/User" }
              }
            }
          },
          "404": {
            "description": "使用者不存在"
          }
        }
      },
      "put": {
        "tags": ["User"],
        "summary": "更新使用者",
        "operationId": "updateUser",
        "parameters": [
          {
            "name": "id",
            "in": "path",
            "required": true,
            "schema": { "type": "integer" }
          }
        ],
        "requestBody": {
          "required": true,
          "content": {
            "application/json": {
              "schema": { "$ref": "#/components/schemas/UpdateUserRequest" }
            }
          }
        },
        "responses": {
          "200": {
            "description": "更新成功",
            "content": {
              "application/json": {
                "schema": { "$ref": "#/components/schemas/User" }
              }
            }
          }
        }
      },
      "delete": {
        "tags": ["User"],
        "summary": "刪除使用者",
        "operationId": "deleteUser",
        "parameters": [
          {
            "name": "id",
            "in": "path",
            "required": true,
            "schema": { "type": "integer" }
          }
        ],
        "responses": {
          "204": { "description": "刪除成功" }
        }
      }
    },
    "/articles": {
      "get": {
        "tags": ["Article"],
        "summary": "取得文章列表",
        "operationId": "getArticles",
        "parameters": [
          {
            "name": "page",
            "in": "query",
            "schema": { "type": "integer", "default": 1 }
          },
          {
            "name": "status",
            "in": "query",
            "schema": {
              "type": "string",
              "enum": ["draft", "published", "archived"]
            }
          }
        ],
        "responses": {
          "200": {
            "description": "成功",
            "content": {
              "application/json": {
                "schema": { "$ref": "#/components/schemas/ArticleListResponse" }
              }
            }
          }
        }
      }
    }
  },
  "components": {
    "schemas": {
      "User": {
        "type": "object",
        "properties": {
          "id": { "type": "integer", "example": 1 },
          "name": { "type": "string", "example": "Admin" },
          "email": {
            "type": "string",
            "format": "email",
            "example": "admin@modsemi.dev"
          },
          "roles": {
            "type": "array",
            "items": { "type": "string" },
            "example": ["admin"]
          },
          "createdAt": { "type": "string", "format": "date-time" }
        }
      },
      "CreateUserRequest": {
        "type": "object",
        "required": ["name", "email"],
        "properties": {
          "name": { "type": "string" },
          "email": { "type": "string", "format": "email" },
          "roles": {
            "type": "array",
            "items": { "type": "string" }
          }
        }
      },
      "UpdateUserRequest": {
        "type": "object",
        "properties": {
          "name": { "type": "string" },
          "email": { "type": "string", "format": "email" },
          "roles": {
            "type": "array",
            "items": { "type": "string" }
          }
        }
      },
      "UserListResponse": {
        "type": "object",
        "properties": {
          "data": {
            "type": "array",
            "items": { "$ref": "#/components/schemas/User" }
          },
          "total": { "type": "integer" },
          "page": { "type": "integer" },
          "pageSize": { "type": "integer" }
        }
      },
      "Article": {
        "type": "object",
        "properties": {
          "id": { "type": "integer" },
          "title": { "type": "string" },
          "content": { "type": "string" },
          "status": {
            "type": "string",
            "enum": ["draft", "published", "archived"]
          },
          "author": { "$ref": "#/components/schemas/User" },
          "createdAt": { "type": "string", "format": "date-time" }
        }
      },
      "ArticleListResponse": {
        "type": "object",
        "properties": {
          "data": {
            "type": "array",
            "items": { "$ref": "#/components/schemas/Article" }
          },
          "total": { "type": "integer" },
          "page": { "type": "integer" },
          "pageSize": { "type": "integer" }
        }
      }
    }
  }
}
